LICENSE.md
README.md
setup.cfg
setup.py
simple_dataframe_generator/__init__.py
simple_dataframe_generator/simple_dataframe_generator.py
simple_dataframe_generator.egg-info/PKG-INFO
simple_dataframe_generator.egg-info/SOURCES.txt
simple_dataframe_generator.egg-info/dependency_links.txt
simple_dataframe_generator.egg-info/requires.txt
simple_dataframe_generator.egg-info/top_level.txt