Metadata-Version: 2.1
Name: simple-dataframe-generator
Version: 1.0.3
Summary: Generate pandas DataFrame quick and easy.
Home-page: https://github.com/jmatusov/simple_dataframe_generator
Download-URL: https://github.com/jmatusov/simple_dataframe_generator/archive/refs/tags/1.0.3.tar.gz
Author: jmatusov
Author-email: jakub.matusov1@gmail.com
License: MIT
Keywords: pandas,dataframe,generator
Classifier: License :: OSI Approved :: MIT License
Classifier: Programming Language :: Python :: 3
Classifier: Programming Language :: Python :: 3.9
License-File: LICENSE.md
